<?xml version="1.0" encoding="utf-8" ?>
<dwsync>
<file name="session.m.php" server="F:/work/wwwort" local="130379943318043263" remote="130379943310000000" />
<file name="verifycode.m.php" server="F:/work/wwwort" local="130380752044200762" remote="130380752040000000" />
<file name="encode.m.php" server="F:/work/wwwort" local="130379943317887263" remote="130379943310000000" />
<file name="session.m.php" server="F:/work/wwwort/" local="130379943310000000" remote="130379943310000000" />
<file name="verifycode.m.php" server="F:/work/wwwort/" local="130380752044200762" remote="130380752040000000" />
<file name="encode.m.php" server="F:/work/wwwort/" local="130379943310000000" remote="130379943310000000" />
<file name="mysql.m.php" server="F:/work/wwwort/" local="130584292850000000" remote="130584292850000000" />
<file name="session.m.php" server="E:/work/www" local="130374429840000000" remote="130374429840000000" />
<file name="verifycode.m.php" server="E:/work/www" local="130380466520000000" remote="130380466520000000" />
<file name="mysql.m.php" server="E:/work/www" local="130747427160000000" remote="130747427160000000" />
<file name="encode.m.php" server="E:/work/www" local="130357447400000000" remote="130357447400000000" />
</dwsync>